Workbook

Sheet Dashboard
B2: THẢO DƯỢC ZONE — DASHBOARD LỢI NHUẬN THỰC
B3: Tổng hợp doanh thu, chi phí và lợi nhuận thực đa kênh (06/2026 – 08/2026)
B5: Tổng doanh thu | E5: Tổng phí sàn | H5: Lợi nhuận thực | K5: % Biên LN trung bình
B6: =ProductProfitability!D15 -> 104733400 | E6: =ProductProfitability!E15 -> 10561319 | H6: =ProductProfitability!G15 -> 65907881 | K6: =ProductProfitability!H15 -> 0.62929191
B11: Cảnh báo tồn kho khẩn cấp (<=15 ngày đến hạn)
B12: =COUNTIFS(InventoryAlerts!$G$5:$G$37,">0",InventoryAlerts!$H$5:$H$37,"<=15") & " lô hàng cần xử lý ngay — xem chi tiết ở tab InventoryAlerts" -> 1 lô hàng cần xử lý ngay — xem chi tiết ở tab InventoryAlerts
B14: Sản phẩm bán chạy nhưng biên lợi nhuận thấp nhất (dưới ngưỡng cảnh báo)
B15: =INDEX(ProductProfitability!$B$7:$B$14,MATCH(MIN(ProductProfitability!$H$7:$H$14),ProductProfitability!$H$7:$H$14,0)) & " — % biên LN thấp nhất: " & TEXT(MIN(ProductProfitability!$H$7:$H$14),"0.0%") -> Trà cà leo gai giảm cân — % biên LN thấp nhất: 60.2%

Sheet Products
A1: sku_id | B1: sku_name | C1: category | D1: cost_price
A2: SKU001 | B2: Trà atiso thanh lọc | C2: Thanh lọc | D2: 9000
A3: SKU002 | B3: Trà lá nam sen ổi | C3: Thanh lọc | D3: 8500
A4: SKU003 | B4: Trà diếp cá rau má | C4: Detox | D4: 10500
A5: SKU004 | B5: Trà cà leo gai giảm cân | C5: Detox | D5: 15000
A6: SKU005 | B6: Trà hoa cúc an thần | C6: An thần | D6: 9500
A7: SKU006 | B7: Trà hoa đậu biếc | C7: An thần | D7: 8800
A8: SKU007 | B8: Trà gừng mật ong | C8: Giữ ấm | D8: 11000
A9: SKU008 | B9: Trà mâm xôi vitamin | C9: Bổ sung dưỡng chất | D9: 9800

Sheet PlatformFees
A1: channel | B1: fee_type | C1: fee_rate
A2: Shopee | B2: commission | C2: 0.13
A3: TikTok Shop | B3: commission | C3: 0.16
A4: Zalo/Fanpage | B4: commission | C4: 0
A5: Đại lý | B5: commission | C5: 0

Sheet RawData
A1: order_id | B1: order_date | C1: channel | D1: sku_id | E1: quantity | F1: revenue | G1: sku_name | H1: category | I1: cost_price | J1: fee_rate | K1: total_cost | L1: platform_fee | M1: net_profit | N1: net_margin_pct
A2: ORD00001 | B2: 2026-06-01 | C2: Shopee | D2: SKU006 | E2: 1 | F2: 32100 | G2: =INDEX(Products!$B$2:$B$9,MATCH(D2,Products!$A$2:$A$9,0)) -> Trà hoa đậu biếc | H2: =INDEX(Products!$C$2:$C$9,MATCH(D2,Products!$A$2:$A$9,0)) -> An thần | I2: =INDEX(Products!$D$2:$D$9,MATCH(D2,Products!$A$2:$A$9,0)) -> 8800 | J2: =IFERROR(INDEX(PlatformFees!$C$2:$C$5,MATCH(C2,PlatformFees!$A$2:$A$5,0)),0) -> 0.13 | K2: =E2*I2 -> 8800 | L2: =F2*J2 -> 4173 | M2: =F2-L2-K2 -> 19127 | N2: =IFERROR(M2/F2,0) -> 0.5958567
A3: ORD00002 | B3: 2026-06-01 | C3: Zalo/Fanpage | D3: SKU006 | E3: 2 | F3: 63200 | G3: =INDEX(Products!$B$2:$B$9,MATCH(D3,Products!$A$2:$A$9,0)) -> Trà hoa đậu biếc | H3: =INDEX(Products!$C$2:$C$9,MATCH(D3,Products!$A$2:$A$9,0)) -> An thần | I3: =INDEX(Products!$D$2:$D$9,MATCH(D3,Products!$A$2:$A$9,0)) -> 8800 | J3: =IFERROR(INDEX(PlatformFees!$C$2:$C$5,MATCH(C3,PlatformFees!$A$2:$A$5,0)),0) -> 0 | K3: =E3*I3 -> 17600 | L3: =F3*J3 -> 0 | M3: =F3-L3-K3 -> 45600 | N3: =IFERROR(M3/F3,0) -> 0.72151899
A4: ORD00003 | B4: 2026-06-01 | C4: Shopee | D4: SKU001 | E4: 1 | F4: 33100 | G4: =INDEX(Products!$B$2:$B$9,MATCH(D4,Products!$A$2:$A$9,0)) -> Trà atiso thanh lọc | H4: =INDEX(Products!$C$2:$C$9,MATCH(D4,Products!$A$2:$A$9,0)) -> Thanh lọc | I4: =INDEX(Products!$D$2:$D$9,MATCH(D4,Products!$A$2:$A$9,0)) -> 9000 | J4: =IFERROR(INDEX(PlatformFees!$C$2:$C$5,MATCH(C4,PlatformFees!$A$2:$A$5,0)),0) -> 0.13 | K4: =E4*I4 -> 9000 | L4: =F4*J4 -> 4303 | M4: =F4-L4-K4 -> 19797 | N4: =IFERROR(M4/F4,0) -> 0.59809668
A5: ORD00004 | B5: 2026-06-01 | C5: TikTok Shop | D5: SKU004 | E5: 3 | F5: 163600 | G5: =INDEX(Products!$B$2:$B$9,MATCH(D5,Products!$A$2:$A$9,0)) -> Trà cà leo gai giảm cân | H5: =INDEX(Products!$C$2:$C$9,MATCH(D5,Products!$A$2:$A$9,0)) -> Detox | I5: =INDEX(Products!$D$2:$D$9,MATCH(D5,Products!$A$2:$A$9,0)) -> 15000 | J5: =IFERROR(INDEX(PlatformFees!$C$2:$C$5,MATCH(C5,PlatformFees!$A$2:$A$5,0)),0) -> 0.16 | K5: =E5*I5 -> 45000 | L5: =F5*J5 -> 26176 | M5: =F5-L5-K5 -> 92424 | N5: =IFERROR(M5/F5,0) -> 0.56493888
A6: ORD00005 | B6: 2026-06-01 | C6: TikTok Shop | D6: SKU003 | E6: 2 | F6: 79900 | G6: =INDEX(Products!$B$2:$B$9,MATCH(D6,Products!$A$2:$A$9,0)) -> Trà diếp cá rau má | H6: =INDEX(Products!$C$2:$C$9,MATCH(D6,Products!$A$2:$A$9,0)) -> Detox | I6: =INDEX(Products!$D$2:$D$9,MATCH(D6,Products!$A$2:$A$9,0)) -> 10500 | J6: =IFERROR(INDEX(PlatformFees!$C$2:$C$5,MATCH(C6,PlatformFees!$A$2:$A$5,0)),0) -> 0.16 | K6: =E6*I6 -> 21000 | L6: =F6*J6 -> 12784 | M6: =F6-L6-K6 -> 46116 | N6: =IFERROR(M6/F6,0) -> 0.57717146
A7: ORD00006 | B7: 2026-06-01 | C7: Zalo/Fanpage | D7: SKU007 | E7: 1 | F7: 39900 | G7: =INDEX(Products!$B$2:$B$9,MATCH(D7,Products!$A$2:$A$9,0)) -> Trà gừng mật ong | H7: =INDEX(Products!$C$2:$C$9,MATCH(D7,Products!$A$2:$A$9,0)) -> Giữ ấm | I7: =INDEX(Products!$D$2:$D$9,MATCH(D7,Products!$A$2:$A$9,0)) -> 11000 | J7: =IFERROR(INDEX(PlatformFees!$C$2:$C$5,MATCH(C7,PlatformFees!$A$2:$A$5,0)),0) -> 0 | K7: =E7*I7 -> 11000 | L7: =F7*J7 -> 0 | M7: =F7-L7-K7 -> 28900 | N7: =IFERROR(M7/F7,0) -> 0.72431078
A8: ORD00007 | B8: 2026-06-01 | C8: Shopee | D8: SKU002 | E8: 1 | F8: 29800 | G8: =INDEX(Products!$B$2:$B$9,MATCH(D8,Products!$A$2:$A$9,0)) -> Trà lá nam sen ổi | H8: =INDEX(Products!$C$2:$C$9,MATCH(D8,Products!$A$2:$A$9,0)) -> Thanh lọc | I8: =INDEX(Products!$D$2:$D$9,MATCH(D8,Products!$A$2:$A$9,0)) -> 8500 | J8: =IFERROR(INDEX(PlatformFees!$C$2:$C$5,MATCH(C8,PlatformFees!$A$2:$A$5,0)),0) -> 0.13 | K8: =E8*I8 -> 8500 | L8: =F8*J8 -> 3874 | M8: =F8-L8-K8 -> 17426 | N8: =IFERROR(M8/F8,0) -> 0.5847651
A9: ORD00008 | B9: 2026-06-01 | C9: Shopee | D9: SKU003 | E9: 1 | F9: 41400 | G9: =INDEX(Products!$B$2:$B$9,MATCH(D9,Products!$A$2:$A$9,0)) -> Trà diếp cá rau má | H9: =INDEX(Products!$C$2:$C$9,MATCH(D9,Products!$A$2:$A$9,0)) -> Detox | I9: =INDEX(Products!$D$2:$D$9,MATCH(D9,Products!$A$2:$A$9,0)) -> 10500 | J9: =IFERROR(INDEX(PlatformFees!$C$2:$C$5,MATCH(C9,PlatformFees!$A$2:$A$5,0)),0) -> 0.13 | K9: =E9*I9 -> 10500 | L9: =F9*J9 -> 5382 | M9: =F9-L9-K9 -> 25518 | N9: =IFERROR(M9/F9,0) -> 0.61637681
A10: ORD00009 | B10: 2026-06-01 | C10: Zalo/Fanpage | D10: SKU007 | E10: 2 | F10: 74700 | G10: =INDEX(Products!$B$2:$B$9,MATCH(D10,Products!$A$2:$A$9,0)) -> Trà gừng mật ong | H10: =INDEX(Products!$C$2:$C$9,MATCH(D10,Products!$A$2:$A$9,0)) -> Giữ ấm | I10: =INDEX(Products!$D$2:$D$9,MATCH(D10,Products!$A$2:$A$9,0)) -> 11000 | J10: =IFERROR(INDEX(PlatformFees!$C$2:$C$5,MATCH(C10,PlatformFees!$A$2:$A$5,0)),0) -> 0 | K10: =E10*I10 -> 22000 | L10: =F10*J10 -> 0 | M10: =F10-L10-K10 -> 52700 | N10: =IFERROR(M10/F10,0) -> 0.70548862
A11: ORD00010 | B11: 2026-06-01 | C11: Đại lý | D11: SKU001 | E11: 1 | F11: 35400 | G11: =INDEX(Products!$B$2:$B$9,MATCH(D11,Products!$A$2:$A$9,0)) -> Trà atiso thanh lọc | H11: =INDEX(Products!$C$2:$C$9,MATCH(D11,Products!$A$2:$A$9,0)) -> Thanh lọc | I11: =INDEX(Products!$D$2:$D$9,MATCH(D11,Products!$A$2:$A$9,0)) -> 9000 | J11: =IFERROR(INDEX(PlatformFees!$C$2:$C$5,MATCH(C11,PlatformFees!$A$2:$A$5,0)),0) -> 0 | K11: =E11*I11 -> 9000 | L11: =F11*J11 -> 0 | M11: =F11-L11-K11 -> 26400 | N11: =IFERROR(M11/F11,0) -> 0.74576271
A12: ORD00011 | B12: 2026-06-01 | C12: TikTok Shop | D12: SKU007 | E12: 2 | F12: 75300 | G12: =INDEX(Products!$B$2:$B$9,MATCH(D12,Products!$A$2:$A$9,0)) -> Trà gừng mật ong | H12: =INDEX(Products!$C$2:$C$9,MATCH(D12,Products!$A$2:$A$9,0)) -> Giữ ấm | I12: =INDEX(Products!$D$2:$D$9,MATCH(D12,Products!$A$2:$A$9,0)) -> 11000 | J12: =IFERROR(INDEX(PlatformFees!$C$2:$C$5,MATCH(C12,PlatformFees!$A$2:$A$5,0)),0) -> 0.16 | K12: =E12*I12 -> 22000 | L12: =F12*J12 -> 12048 | M12: =F12-L12-K12 -> 41252 | N12: =IFERROR(M12/F12,0) -> 0.54783533
A13: ORD00012 | B13: 2026-06-01 | C13: Shopee | D13: SKU005 | E13: 1 | F13: 39100 | G13: =INDEX(Products!$B$2:$B$9,MATCH(D13,Products!$A$2:$A$9,0)) -> Trà hoa cúc an thần | H13: =INDEX(Products!$C$2:$C$9,MATCH(D13,Products!$A$2:$A$9,0)) -> An thần | I13: =INDEX(Products!$D$2:$D$9,MATCH(D13,Products!$A$2:$A$9,0)) -> 9500 | J13: =IFERROR(INDEX(PlatformFees!$C$2:$C$5,MATCH(C13,PlatformFees!$A$2:$A$5,0)),0) -> 0.13 | K13: =E13*I13 -> 9500 | L13: =F13*J13 -> 5083 | M13: =F13-L13-K13 -> 24517 | N13: =IFERROR(M13/F13,0) -> 0.62703325
... A1587: ORD01586 | B1587: 2026-08-31 | C1587: Shopee | D1587: SKU008 | E1587: 2 | F1587: 67200 | G1587: =INDEX(Products!$B$2:$B$9,MATCH(D1587,Products!$A$2:$A$9,0)) -> Trà mâm xôi vitamin | H1587: =INDEX(Products!$C$2:$C$9,MATCH(D1587,Products!$A$2:$A$9,0)) -> Bổ sung dưỡng chất | I1587: =INDEX(Products!$D$2:$D$9,MATCH(D1587,Products!$A$2:$A$9,0)) -> 9800 | J1587: =IFERROR(INDEX(PlatformFees!$C$2:$C$5,MATCH(C1587,PlatformFees!$A$2:$A$5,0)),0) -> 0.13 | K1587: =E1587*I1587 -> 19600 | L1587: =F1587*J1587 -> 8736 | M1587: =F1587-L1587-K1587 -> 38864 | N1587: =IFERROR(M1587/F1587,0) -> 0.57833333

Sheet ProductProfitability
A1: Bảng phân tích lợi nhuận thực theo sản phẩm (SKU)
A4: Ngưỡng cảnh báo % biên lợi nhuận thấp | B4: 0.3
A6: sku_id | B6: sku_name | C6: category | D6: Doanh thu | E6: Phí sàn | F6: Chi phí nguyên liệu | G6: Lợi nhuận thực | H6: % Biên LN
A7: SKU004 | B7: Trà cà leo gai giảm cân | C7: Detox | D7: =SUMIF(RawData!$D$2:$D$1587,A7,RawData!$F$2:$F$1587) -> 24059300 | E7: =SUMIF(RawData!$D$2:$D$1587,A7,RawData!$L$2:$L$1587) -> 2849678 | F7: =SUMIF(RawData!$D$2:$D$1587,A7,RawData!$K$2:$K$1587) -> 6735000 | G7: =D7-E7-F7 -> 14474622 | H7: =IFERROR(G7/D7,0) -> 0.60162274
A8: SKU003 | B8: Trà diếp cá rau má | C8: Detox | D8: =SUMIF(RawData!$D$2:$D$1587,A8,RawData!$F$2:$F$1587) -> 17615700 | E8: =SUMIF(RawData!$D$2:$D$1587,A8,RawData!$L$2:$L$1587) -> 2209826 | F8: =SUMIF(RawData!$D$2:$D$1587,A8,RawData!$K$2:$K$1587) -> 4515000 | G8: =D8-E8-F8 -> 10890874 | H8: =IFERROR(G8/D8,0) -> 0.61824815
A9: SKU005 | B9: Trà hoa cúc an thần | C9: An thần | D9: =SUMIF(RawData!$D$2:$D$1587,A9,RawData!$F$2:$F$1587) -> 11218300 | E9: =SUMIF(RawData!$D$2:$D$1587,A9,RawData!$L$2:$L$1587) -> 995443 | F9: =SUMIF(RawData!$D$2:$D$1587,A9,RawData!$K$2:$K$1587) -> 2869000 | G9: =D9-E9-F9 -> 7353857 | H9: =IFERROR(G9/D9,0) -> 0.6555233
A10: SKU008 | B10: Trà mâm xôi vitamin | C10: Bổ sung dưỡng chất | D10: =SUMIF(RawData!$D$2:$D$1587,A10,RawData!$F$2:$F$1587) -> 11175400 | E10: =SUMIF(RawData!$D$2:$D$1587,A10,RawData!$L$2:$L$1587) -> 1067192 | F10: =SUMIF(RawData!$D$2:$D$1587,A10,RawData!$K$2:$K$1587) -> 3116400 | G10: =D10-E10-F10 -> 6991808 | H10: =IFERROR(G10/D10,0) -> 0.62564275
A11: SKU007 | B11: Trà gừng mật ong | C11: Giữ ấm | D11: =SUMIF(RawData!$D$2:$D$1587,A11,RawData!$F$2:$F$1587) -> 10753800 | E11: =SUMIF(RawData!$D$2:$D$1587,A11,RawData!$L$2:$L$1587) -> 929088 | F11: =SUMIF(RawData!$D$2:$D$1587,A11,RawData!$K$2:$K$1587) -> 3036000 | G11: =D11-E11-F11 -> 6788712 | H11: =IFERROR(G11/D11,0) -> 0.63128494
A12: SKU001 | B12: Trà atiso thanh lọc | C12: Thanh lọc | D12: =SUMIF(RawData!$D$2:$D$1587,A12,RawData!$F$2:$F$1587) -> 10263600 | E12: =SUMIF(RawData!$D$2:$D$1587,A12,RawData!$L$2:$L$1587) -> 759700 | F12: =SUMIF(RawData!$D$2:$D$1587,A12,RawData!$K$2:$K$1587) -> 2709000 | G12: =D12-E12-F12 -> 6794900 | H12: =IFERROR(G12/D12,0) -> 0.66203866
A13: SKU006 | B13: Trà hoa đậu biếc | C13: An thần | D13: =SUMIF(RawData!$D$2:$D$1587,A13,RawData!$F$2:$F$1587) -> 9952400 | E13: =SUMIF(RawData!$D$2:$D$1587,A13,RawData!$L$2:$L$1587) -> 874629 | F13: =SUMIF(RawData!$D$2:$D$1587,A13,RawData!$K$2:$K$1587) -> 2648800 | G13: =D13-E13-F13 -> 6428971 | H13: =IFERROR(G13/D13,0) -> 0.64597193
A14: SKU002 | B14: Trà lá nam sen ổi | C14: Thanh lọc | D14: =SUMIF(RawData!$D$2:$D$1587,A14,RawData!$F$2:$F$1587) -> 9694900 | E14: =SUMIF(RawData!$D$2:$D$1587,A14,RawData!$L$2:$L$1587) -> 875763 | F14: =SUMIF(RawData!$D$2:$D$1587,A14,RawData!$K$2:$K$1587) -> 2635000 | G14: =D14-E14-F14 -> 6184137 | H14: =IFERROR(G14/D14,0) -> 0.63787527
B15: TỔNG CỘNG | D15: =SUM(D7:D14) -> 104733400 | E15: =SUM(E7:E14) -> 10561319 | F15: =SUM(F7:F14) -> 28264200 | G15: =SUM(G7:G14) -> 65907881 | H15: =IFERROR(G15/D15,0) -> 0.62929191

Sheet InventoryAlerts
A1: Cảnh báo tồn kho theo lô — Hạn sử dụng
A2: Ngày tham chiếu (hôm nay) | B2: 46265
A4: batch_id | B4: sku_id | C4: sku_name | D4: import_date | E4: expiry_date | F4: quantity_in | G4: quantity_remaining | H4: days_to_expiry | I4: Mức cảnh báo
A5: BATCH9001 | B5: SKU004 | C5: =IFERROR(INDEX(Products!$B$2:$B$9,MATCH(B5,Products!$A$2:$A$9,0)),"") -> Trà cà leo gai giảm cân | D5: 2025-09-25 | E5: 2026-09-10 | F5: 150 | G5: 42 | H5: =E5-$B$2 -> 10 | I5: =IF(G5=0,"Hết hàng",IF(H5<=15,"Khẩn cấp (<=15 ngày)",IF(H5<=30,"Cảnh báo (<=30 ngày)","Bình thường"))) -> Khẩn cấp (<=15 ngày)
A6: BATCH9002 | B6: SKU003 | C6: =IFERROR(INDEX(Products!$B$2:$B$9,MATCH(B6,Products!$A$2:$A$9,0)),"") -> Trà diếp cá rau má | D6: 2025-09-15 | E6: 2026-09-18 | F6: 120 | G6: 25 | H6: =E6-$B$2 -> 18 | I6: =IF(G6=0,"Hết hàng",IF(H6<=15,"Khẩn cấp (<=15 ngày)",IF(H6<=30,"Cảnh báo (<=30 ngày)","Bình thường"))) -> Cảnh báo (<=30 ngày)
A7: BATCH9003 | B7: SKU007 | C7: =IFERROR(INDEX(Products!$B$2:$B$9,MATCH(B7,Products!$A$2:$A$9,0)),"") -> Trà gừng mật ong | D7: 2025-09-10 | E7: 2026-09-25 | F7: 100 | G7: 30 | H7: =E7-$B$2 -> 25 | I7: =IF(G7=0,"Hết hàng",IF(H7<=15,"Khẩn cấp (<=15 ngày)",IF(H7<=30,"Cảnh báo (<=30 ngày)","Bình thường"))) -> Cảnh báo (<=30 ngày)
A8: BATCH0010 | B8: SKU003 | C8: =IFERROR(INDEX(Products!$B$2:$B$9,MATCH(B8,Products!$A$2:$A$9,0)),"") -> Trà diếp cá rau má | D8: 2026-06-06 | E8: 2027-04-02 | F8: 109 | G8: 51 | H8: =E8-$B$2 -> 214 | I8: =IF(G8=0,"Hết hàng",IF(H8<=15,"Khẩn cấp (<=15 ngày)",IF(H8<=30,"Cảnh báo (<=30 ngày)","Bình thường"))) -> Bình thường
A9: BATCH0021 | B9: SKU006 | C9: =IFERROR(INDEX(Products!$B$2:$B$9,MATCH(B9,Products!$A$2:$A$9,0)),"") -> Trà hoa đậu biếc | D9: 2026-07-07 | E9: 2027-05-03 | F9: 188 | G9: 40 | H9: =E9-$B$2 -> 245 | I9: =IF(G9=0,"Hết hàng",IF(H9<=15,"Khẩn cấp (<=15 ngày)",IF(H9<=30,"Cảnh báo (<=30 ngày)","Bình thường"))) -> Bình thường
A10: BATCH0006 | B10: SKU002 | C10: =IFERROR(INDEX(Products!$B$2:$B$9,MATCH(B10,Products!$A$2:$A$9,0)),"") -> Trà lá nam sen ổi | D10: 2026-07-11 | E10: 2027-05-07 | F10: 81 | G10: 6 | H10: =E10-$B$2 -> 249 | I10: =IF(G10=0,"Hết hàng",IF(H10<=15,"Khẩn cấp (<=15 ngày)",IF(H10<=30,"Cảnh báo (<=30 ngày)","Bình thường"))) -> Bình thường
A11: BATCH0012 | B11: SKU004 | C11: =IFERROR(INDEX(Products!$B$2:$B$9,MATCH(B11,Products!$A$2:$A$9,0)),"") -> Trà cà leo gai giảm cân | D11: 2026-07-12 | E11: 2027-05-08 | F11: 129 | G11: 39 | H11: =E11-$B$2 -> 250 | I11: =IF(G11=0,"Hết hàng",IF(H11<=15,"Khẩn cấp (<=15 ngày)",IF(H11<=30,"Cảnh báo (<=30 ngày)","Bình thường"))) -> Bình thường
A12: BATCH0001 | B12: SKU001 | C12: =IFERROR(INDEX(Products!$B$2:$B$9,MATCH(B12,Products!$A$2:$A$9,0)),"") -> Trà atiso thanh lọc | D12: 2026-07-18 | E12: 2027-05-14 | F12: 132 | G12: 41 | H12: =E12-$B$2 -> 256 | I12: =IF(G12=0,"Hết hàng",IF(H12<=15,"Khẩn cấp (<=15 ngày)",IF(H12<=30,"Cảnh báo (<=30 ngày)","Bình thường"))) -> Bình thường
A13: BATCH0003 | B13: SKU001 | C13: =IFERROR(INDEX(Products!$B$2:$B$9,MATCH(B13,Products!$A$2:$A$9,0)),"") -> Trà atiso thanh lọc | D13: 2026-06-19 | E13: 2027-05-15 | F13: 194 | G13: 63 | H13: =E13-$B$2 -> 257 | I13: =IF(G13=0,"Hết hàng",IF(H13<=15,"Khẩn cấp (<=15 ngày)",IF(H13<=30,"Cảnh báo (<=30 ngày)","Bình thường"))) -> Bình thường
A14: BATCH0030 | B14: SKU008 | C14: =IFERROR(INDEX(Products!$B$2:$B$9,MATCH(B14,Products!$A$2:$A$9,0)),"") -> Trà mâm xôi vitamin | D14: 2026-06-20 | E14: 2027-05-16 | F14: 156 | G14: 12 | H14: =E14-$B$2 -> 258 | I14: =IF(G14=0,"Hết hàng",IF(H14<=15,"Khẩn cấp (<=15 ngày)",IF(H14<=30,"Cảnh báo (<=30 ngày)","Bình thường"))) -> Bình thường
A15: BATCH0022 | B15: SKU006 | C15: =IFERROR(INDEX(Products!$B$2:$B$9,MATCH(B15,Products!$A$2:$A$9,0)),"") -> Trà hoa đậu biếc | D15: 2026-07-24 | E15: 2027-05-20 | F15: 102 | G15: 58 | H15: =E15-$B$2 -> 262 | I15: =IF(G15=0,"Hết hàng",IF(H15<=15,"Khẩn cấp (<=15 ngày)",IF(H15<=30,"Cảnh báo (<=30 ngày)","Bình thường"))) -> Bình thường
A16: BATCH0015 | B16: SKU005 | C16: =IFERROR(INDEX(Products!$B$2:$B$9,MATCH(B16,Products!$A$2:$A$9,0)),"") -> Trà hoa cúc an thần | D16: 2026-06-25 | E16: 2027-05-21 | F16: 161 | G16: 46 | H16: =E16-$B$2 -> 263 | I16: =IF(G16=0,"Hết hàng",IF(H16<=15,"Khẩn cấp (<=15 ngày)",IF(H16<=30,"Cảnh báo (<=30 ngày)","Bình thường"))) -> Bình thường
... A37: BATCH0007 | B37: SKU002 | C37: =IFERROR(INDEX(Products!$B$2:$B$9,MATCH(B37,Products!$A$2:$A$9,0)),"") -> Trà lá nam sen ổi | D37: 2026-08-09 | E37: 2027-08-09 | F37: 164 | G37: 43 | H37: =E37-$B$2 -> 343 | I37: =IF(G37=0,"Hết hàng",IF(H37<=15,"Khẩn cấp (<=15 ngày)",IF(H37<=30,"Cảnh báo (<=30 ngày)","Bình thường"))) -> Bình thường
